azureml/__init__.py
azureml/train/__init__.py
azureml/train/automl/__init__.py
azureml/train/automl/runtime/ThirdPartyNotice.txt
azureml/train/automl/runtime/__init__.py
azureml/train/automl/runtime/_azureautomlruncontext.py
azureml/train/automl/runtime/_cachestorefactory.py
azureml/train/automl/runtime/_data_characteristics_calculator.py
azureml/train/automl/runtime/_data_preparer.py
azureml/train/automl/runtime/_ensemble_helper.py
azureml/train/automl/runtime/_partitioned_dataset_utils.py
azureml/train/automl/runtime/_problem_info_utils.py
azureml/train/automl/runtime/_remote_script.py
azureml/train/automl/runtime/_version.py
azureml/train/automl/runtime/_worker_initiator.py
azureml/train/automl/runtime/automl_explain_utilities.py
azureml/train/automl/runtime/automl_step.py
azureml/train/automl/runtime/automlexplainer.py
azureml/train/automl/runtime/ensemble.py
azureml/train/automl/runtime/run.py
azureml/train/automl/runtime/stack_ensemble.py
azureml/train/automl/runtime/utilities.py
azureml/train/automl/runtime/_automl_job_phases/__init__.py
azureml/train/automl/runtime/_automl_job_phases/batch_training_phase.py
azureml/train/automl/runtime/_automl_job_phases/experiment_preparation_phase.py
azureml/train/automl/runtime/_automl_job_phases/featurization_phase.py
azureml/train/automl/runtime/_automl_job_phases/model_explain_phase.py
azureml/train/automl/runtime/_automl_job_phases/model_test_phase.py
azureml/train/automl/runtime/_automl_job_phases/training_iteration_phase.py
azureml/train/automl/runtime/_automl_job_phases/utilities.py
azureml/train/automl/runtime/_automl_job_phases/distributed/__init__.py
azureml/train/automl/runtime/_automl_job_phases/distributed/constants.py
azureml/train/automl/runtime/_automl_job_phases/distributed/experiment_state_plugin.py
azureml/train/automl/runtime/_automl_job_phases/distributed/classification_regression/__init__.py
azureml/train/automl/runtime/_automl_job_phases/distributed/classification_regression/featurization_phase.py
azureml_train_automl_runtime-1.60.0.dist-info/licenses/LICENSE.txt
azureml_train_automl_runtime-1.60.0.dist-info/METADATA
azureml_train_automl_runtime-1.60.0.dist-info/WHEEL
azureml_train_automl_runtime-1.60.0.dist-info/top_level.txt
azureml_train_automl_runtime-1.60.0.dist-info/RECORD
