Metadata-Version: 2.4
Name: azureml-train-automl-runtime
Version: 1.60.0
Summary: Used for automatically finding the best machine learning model and its parameters.
Home-page: https://docs.microsoft.com/python/api/overview/azure/ml/?view=azure-ml-py
Author: Microsoft Corp
License: https://aka.ms/azureml-sdk-license
Classifier: Development Status :: 5 - Production/Stable
Classifier: Intended Audience :: Developers
Classifier: Intended Audience :: Science/Research
Classifier: License :: Other/Proprietary License
Classifier: Programming Language :: Python :: 3
Classifier: Programming Language :: Python :: 3.8
Classifier: Programming Language :: Python :: 3.9
Classifier: Programming Language :: Python :: 3.10
Classifier: Programming Language :: Python :: 3.11
Classifier: Topic :: Scientific/Engineering :: Artificial Intelligence
Classifier: Operating System :: Microsoft :: Windows
Classifier: Operating System :: MacOS
Classifier: Operating System :: POSIX :: Linux
Requires-Python: >=3.8,<3.12
License-File: LICENSE.txt
Requires-Dist: azure-storage-queue~=12.1
Requires-Dist: gensim<3.9.0; python_version < "3.9"
Requires-Dist: gensim==4.3.2; python_version >= "3.9"
Requires-Dist: smart-open<=1.9.0; python_version < "3.9"
Requires-Dist: smart-open==6.4.0; python_version >= "3.9"
Requires-Dist: lightgbm<4.7.0,>=4.6.0
Requires-Dist: numpy<=1.21.6,>=1.16.0; python_version < "3.8"
Requires-Dist: numpy<=1.23.5,>=1.16.0; python_version >= "3.8"
Requires-Dist: pandas==1.5.3
Requires-Dist: scipy<=1.11.0,>=1.0.0
Requires-Dist: scikit-learn~=1.5.1
Requires-Dist: sklearn_pandas<=1.7.0,>=1.4.0
Requires-Dist: statsmodels<0.14,>=0.13.0
Requires-Dist: skl2onnx==1.15.0
Requires-Dist: onnxmltools==1.12.0
Requires-Dist: keras2onnx<=1.6.0,>=1.4.0
Requires-Dist: onnxconverter-common==1.13.0
Requires-Dist: onnx<=1.17.0,>=1.16.1
Requires-Dist: onnxruntime~=1.17.3
Requires-Dist: jinja2<4
Requires-Dist: boto3<=1.20.19
Requires-Dist: botocore<=1.23.19
Requires-Dist: urllib3<2.0.0
Requires-Dist: dask[complete]<=2023.2.0
Requires-Dist: bokeh<3.0.0
Requires-Dist: pyyaml<7.0.0
Requires-Dist: pyarrow==14.0.2
Requires-Dist: azureml-automl-core~=1.60.0
Requires-Dist: azureml-automl-runtime~=1.60.0
Requires-Dist: azureml-train-automl-client~=1.60.0
Requires-Dist: azureml-core~=1.60.0
Requires-Dist: azureml-telemetry~=1.60.0
Requires-Dist: azureml-interpret~=1.60.0
Requires-Dist: azureml-dataset-runtime[fuse,pandas]~=1.60.0
Requires-Dist: azureml-mlflow~=1.60.0
Provides-Extra: catboost
Requires-Dist: catboost<=1.2,>=1.0.6; extra == "catboost"
Provides-Extra: test
Requires-Dist: filelock; extra == "test"
Requires-Dist: catboost==1.0.6; extra == "test"
Requires-Dist: ipykernel==6.22.0; extra == "test"
Requires-Dist: papermill==2.3.3; extra == "test"
Requires-Dist: black<23,>=22.10.0; extra == "test"
Requires-Dist: azureml-pipeline~=1.60.0; extra == "test"
Requires-Dist: dash>=2.3.1; extra == "test"
Dynamic: author
Dynamic: classifier
Dynamic: description
Dynamic: description-content-type
Dynamic: home-page
Dynamic: license
Dynamic: license-file
Dynamic: provides-extra
Dynamic: requires-dist
Dynamic: requires-python
Dynamic: summary
